memnetai/__init__.py
memnetai/basics/__init__.py
memnetai/basics/request/MemNetAIClient.py
memnetai/basics/request/__init__.py
memnetai/basics/request/common_sense/__init__.py
memnetai/basics/request/common_sense/common_sense.py
memnetai/basics/request/common_sense/task/__init__.py
memnetai/basics/request/common_sense/task/all.py
memnetai/basics/request/common_sense/task/delete.py
memnetai/basics/request/common_sense/task/detail.py
memnetai/basics/request/common_sense/task/progress.py
memnetai/basics/request/dream/__init__.py
memnetai/basics/request/dream/dream.py
memnetai/basics/request/dream/task/__init__.py
memnetai/basics/request/dream/task/all.py
memnetai/basics/request/dream/task/delete.py
memnetai/basics/request/dream/task/detail.py
memnetai/basics/request/memories/__init__.py
memnetai/basics/request/memories/memories.py
memnetai/basics/request/memories/task/__init__.py
memnetai/basics/request/memories/task/all.py
memnetai/basics/request/memories/task/delete.py
memnetai/basics/request/memories/task/detail.py
memnetai/basics/request/memories/task/progress.py
memnetai/basics/request/message/__init__.py
memnetai/basics/request/message/message.py
memnetai/basics/request/recall/__init__.py
memnetai/basics/request/recall/recall.py
memnetai/basics/request/think/__init__.py
memnetai/basics/request/think/think.py
memnetai/basics/request/think/task/__init__.py
memnetai/basics/request/think/task/all.py
memnetai/basics/request/think/task/delete.py
memnetai/basics/request/think/task/detail.py
memnetai/upgrade/MemNetAIClientPlus.py
memnetai/upgrade/__init__.py
memnetai/upgrade/llm_init.py
memnetai/upgrade/config/__init__.py
memnetai/upgrade/config/config.py
memnetai/upgrade/config/openai_config.py
memnetai/upgrade/llm/__init__.py
memnetai/upgrade/llm/base.py
memnetai/upgrade/llm/openai/__init__.py
memnetai/upgrade/llm/openai/openai_provider.py
memnetai/upgrade/memory_message_queue/__init__.py
memnetai/upgrade/memory_message_queue/memory_message_queue.py
memnetai_python_sdk-0.1.3.dist-info/METADATA
memnetai_python_sdk-0.1.3.dist-info/WHEEL
memnetai_python_sdk-0.1.3.dist-info/top_level.txt
memnetai_python_sdk-0.1.3.dist-info/RECORD
