Metadata-Version: 2.4
Name: memnetai-python-sdk
Version: 0.1.3
Summary: MemNet AI Python SDK - 提供记忆网络AI的Python接口
Home-page: 
Author: MemNet AI Team
Author-email: admin@donglizhiyuan.com
License: Apache License 2.0
Classifier: Development Status :: 3 - Alpha
Classifier: Intended Audience :: Developers
Classifier: Topic :: Software Development :: Libraries :: Python Modules
Classifier: License :: OSI Approved :: Apache Software License
Classifier: Programming Language :: Python :: 3.9
Classifier: Programming Language :: Python :: 3.10
Classifier: Programming Language :: Python :: 3.11
Classifier: Programming Language :: Python :: 3.12
Classifier: Programming Language :: Python :: 3.13
Requires-Python: >=3.9
Requires-Dist: requests>=2.32.0
Requires-Dist: loguru>=0.7.0
Requires-Dist: openai>=2.14.0
Dynamic: author
Dynamic: author-email
Dynamic: classifier
Dynamic: description
Dynamic: description-content-type
Dynamic: license
Dynamic: requires-dist
Dynamic: requires-python
Dynamic: summary
